Metadata-Version: 2.1
Name: base-api
Version: 0.1.1
Summary: Easily create maintainable API clients.
Home-page: https://github.com/furious-luke/baseapi
Author: Luke Hodkinson
Author-email: furious.luke@gmail.com
Maintainer: Luke Hodkinson
Maintainer-email: furious.luke@gmail.com
License: MIT
Platform: UNKNOWN
Classifier: Development Status :: 3 - Alpha
Classifier: Intended Audience :: Developers
Classifier: Natural Language :: English
Classifier: Operating System :: OS Independent
Classifier: Programming Language :: Python
Classifier: Programming Language :: Python :: 3.5
Classifier: License :: OSI Approved :: MIT License
